LICENSE
MANIFEST.in
README.md
setup.py
rapid/__init__.py
rapid/email.py
rapid/app/exceptions/__init__.py
rapid/app/exceptions/email_exception.py
rapid/app/helpers/__init__.py
rapid/app/helpers/validator.py
rapid_innovation.egg-info/PKG-INFO
rapid_innovation.egg-info/SOURCES.txt
rapid_innovation.egg-info/dependency_links.txt
rapid_innovation.egg-info/top_level.txt