Metadata-Version: 2.1
Name: rapid-innovation
Version: 1.8.8
Summary: Rapid Innovation package
Home-page: https://github.com/Rapid-Python/python-package-rapid
Author: Abhishek Negi
Author-email: abhisheknegi@rapidinnovation.dev
License: MIT
Classifier: Programming Language :: Python :: 3.7
Classifier: License :: OSI Approved :: MIT License
Classifier: Operating System :: OS Independent
Requires-Python: >=3.7
License-File: LICENSE
